README.txt
setup.cfg
setup.py
repoze/__init__.py
repoze.django.egg-info/PKG-INFO
repoze.django.egg-info/SOURCES.txt
repoze.django.egg-info/dependency_links.txt
repoze.django.egg-info/entry_points.txt
repoze.django.egg-info/namespace_packages.txt
repoze.django.egg-info/not-zip-safe
repoze.django.egg-info/requires.txt
repoze.django.egg-info/top_level.txt
repoze/django/__init__.py